{
	"core:tower" :
	{
		"town" :
		{
			"hallBackground": "TPTHBKTW",
			"buildingsIcons": "town-screen/tower/ALTHALLTOWR.DEF",
			"hallSlots":
			[	
				[ [ "villageHall", "townHall", "cityHall", "capitol" ], [ "fort", "citadel", "castle" ], [ "tavern" ], [ "blacksmith" ] ],
				[ [ "marketplace", "resourceSilo" ], [ "mageGuild1", "mageGuild2", "mageGuild3", "mageGuild4", "mageGuild5" ], [ "special3" ], [ "special4" ] ],
				[ [ "special1" ], [ "special2" ], [ "horde1", "horde1Upgr", "horde1Upgr2" ] ],
				[ [ "dwellingLvl1", "dwellingUpLvl1", "dwellingUp2Lvl1" ], [ "dwellingLvl2", "dwellingUpLvl2", "dwellingUp2Lvl2" ], [ "dwellingLvl3", "dwellingUpLvl3", "dwellingUp2Lvl3" ], [ "dwellingLvl4", "dwellingUpLvl4", "dwellingUp2Lvl4" ] ],
				[ [ "dwellingLvl5", "dwellingUpLvl5", "dwellingUp2Lvl5" ], [ "dwellingLvl6", "dwellingUpLvl6", "dwellingUp2Lvl6" ], [ "dwellingLvl7", "dwellingUpLvl7", "dwellingUp2Lvl7" ] ]
			],
			"creatures" :
			[
				["gremlin", "masterGremlin", "tumGrandmasterGremlin"],
				["stoneGargoyle", "obsidianGargoyle", "tumMarbleGargoyle"],
				["ironGolem", "stoneGolem", "tumSteelGolem"],
				["mage", "archMage", "tumSupremeArchMage"],
				["genie", "masterGenie", "tumArcaneGenie"],
				["naga", "nagaQueen", "tumNagaEmpress"],
				["giant", "titan", "lordOfThunder"]
			],

			"structures" :
			{
				"extraCapitol":{ "animation" : "town-screen/tower/TBTWEXT5.def", "x" : 430, "y" : 28,  "z" : 0 },				
				"horde1":         { "y" : 47 },
				"horde1Upgr":     { "y" : 28 },
				"horde1Upgr2":     	{ "animation" : "town-screen/tower/TBTWHRD2U.def", "x" : 0,   "y" : 8,  "border" : "town-screen/tower/borders/TOTGAR2HU.bmp", "area" : "town-screen/tower/areas/TZTGAR2HU.bmp", "hidden" : true, "builds" : "horde1Upgr" },
				"dwellingUp2Lvl1": 	{ "animation" : "town-screen/tower/TBTWUP2_0.def", "x" : 440, "y" : 221, "z" : 1,  "border" : "town-screen/tower/borders/TOTGRM2AU.bmp", "area" : "town-screen/tower/areas/TZTGRM2AU.bmp" },
				"dwellingUp2Lvl2": 	{ "animation" : "town-screen/tower/TBTWUP2_1.def", "x" : 4,   "y" : 8,  "border" : "town-screen/tower/borders/TOTGAR2U.bmp",  "area" : "town-screen/tower/areas/TZTGAR2U.bmp" },
				"dwellingUp2Lvl3": 	{ "animation" : "town-screen/tower/TBTWUP2_2.def", "x" : 209, "y" : 177, "z" : 1,  "border" : "town-screen/tower/borders/TOTGOL2AU.bmp", "area" : "town-screen/tower/areas/TZTGOL2AU.bmp" },
				"dwellingUp2Lvl4": 	{ "animation" : "town-screen/tower/TBTWUP2_3.def", "x" : 610, "y" : 37,  "border" : "town-screen/tower/borders/TOTMAG2U.bmp",  "area" : "town-screen/tower/areas/TZTMAG2U.bmp" },
				"dwellingUp2Lvl5": 	{ "animation" : "town-screen/tower/TBTWUP2_4.def", "x" : 511, "y" : 8,   "border" : "town-screen/tower/borders/TOTGEN2U.bmp",  "area" : "town-screen/tower/areas/TZTGEN2U.bmp" },
				"dwellingUp2Lvl6": { "animation" : "town-screen/tower/TBTWUP2_5.def", "x" : 681, "y" : 118, "z" : 2,  "border" : "town-screen/tower/borders/TOTNag2U.bmp",  "area" : "town-screen/tower/areas/TZTNag2U.bmp" },
				"dwellingUp2Lvl7": { "animation" : "town-screen/tower/TBTWUP2_6.def", "x" : 75,  "y" : 7,  "z" : -1, "border" : "town-screen/tower/borders/TOTTit2U.bmp",  "area" : "town-screen/tower/areas/TZTTit2U.bmp" },
			
			},

			"buildings" :
			{
				"extraCapitol":   {
					"name" : "Geomancy",
					"description" : "Geomancy mark unlocks 3rd level structures to build.",
					"id" : 29, 
					"requires" : 
					[ 
						"allOf", ["castle"], ["dwellingUpLvl6"]
					],
					"mode" : "auto" 
				},
				"dwellingUp2Lvl1":
				{
					"description" : "The Workshop allows you to recruit Grandmaster Gremlins.",
					"name" : "{Adv. Workshop}",
					"requires" : 
					[ 
						"allOf", ["castle"],["dwellingUpLvl6"]
					],
					"upgrades" : "dwellingUpLvl1",					
					"cost" :
					{
						"wood":    5,
						"ore":     5,
						"gold":	1300
					},
					"id" : 44					
				},
				"dwellingUp2Lvl2":
				{
					"description" : "The Parapet allows you to recruit Marble Gargoyles.",
					"name" : "{Adv. Parapet}",
					"requires" : 
					[ 
						"allOf",["castle"],["dwellingUpLvl6"]
					],					
					"cost" :
					{
						"ore":    15,
						"gold":	2500
					},
					"id" : 45, 
					"upgrades" : "dwellingUpLvl2"
				},
				"horde1Upgr2" :
				{
					"description" : "The Sculptor's Wings increase Marble Gargoyle production by 4 per week.",
					"name" : "{Sculptor's Wings}",				
					"cost" :
					{
						"gold":	1000
					},
					"requires" : [ "horde1Upgr" ],
					"upgrades" : "dwellingUp2Lvl2",
					"id" : 20,
					"mode" : "auto" 
				},

				"dwellingUp2Lvl3":
				{
					"description" : "The Golem Factory allows you to recruit Mithril Golems.",
					"name" : "{Adv. Golem Factory}",
					"requires" : 
					[ 
						"allOf",["castle"],["dwellingUpLvl6"]
					],				
					"cost" :
					{
						"wood":    10,
						"mercury": 5,
						"ore":     10,
						"gold":	4000
					},
					"id" : 46, 
					"upgrades" : "dwellingUpLvl3"
				},
				"dwellingUp2Lvl4":
				{
					"description" : "The Mage Tower allows you to recruit Supreme Arch Magi.",
					"name" : "{Adv. Mage Towers}",
					"requires" : 
					[ 
						"allOf",["dwellingUp2Lvl3"],["mageGuild2"]
					],						
					"cost" :
					{
						"wood":    10,
						"mercury": 5,
						"ore":     5,
						"crystal": 5,
						"sulfur":  5,
						"gems":    5,
						"gold":	4500
					},
					"id" : 47, 
					"upgrades" : "dwellingUpLvl4"
				},
				"dwellingUp2Lvl5":
				{
					"description" : "The Altar of Wishes allows you to recruit Arcane Genies.",
					"name" : "{Adv. Altar of Wishes}",
					"requires" : 
					[ 
						"dwellingUp2Lvl6"
					],					
					"cost" :
					{
						"wood":    10,
						"ore":     5,
						"crystal": 6,
						"gems":    6,
						"gold":	5000
					},
					"id" : 48, 
					"upgrades" : "dwellingUpLvl5"
				},
				"dwellingUp2Lvl6":
				{
					"description" : "The Golden Pavilion allows you to recruit Naga Empresses.",
					"name" : "{Adv. Golden Pavilion}",
					"requires" : 
					[ 
						"allOf", ["castle"],["special3"],["mageGuild3"]
					],					
					"cost" :
					{
						"wood":    5,
						"ore":     5,
						"mercury": 5,
						"sulfur":  5,
						"crystal": 5,
						"gems":    5,
						"gold":	7000
					},
					"id" : 49, 
					"upgrades" : "dwellingUpLvl6"
				},
				"dwellingUp2Lvl7":
				{
					"description" : "The Cloud Temple allows you to recruit Lords of Thunder.",
					"name" : "{Adv. Cloud Temple}",
					"requires" : 
					[ 
						"dwellingUp2Lvl6"
					],					
					"cost" :
					{
						"wood":    15,
						"ore":     15,
						"gems":    40,
						"gold":	30000
					},
					"id" : 50, 
					"upgrades" : "dwellingUpLvl7"
				}			
			}
		}
	}
}
